sound_to_midi/__init__.py
sound_to_midi/cli.py
sound_to_midi/monophonic.py
sound_to_midi-0.0.3.dist-info/LICENSE
sound_to_midi-0.0.3.dist-info/METADATA
sound_to_midi-0.0.3.dist-info/WHEEL
sound_to_midi-0.0.3.dist-info/entry_points.txt
sound_to_midi-0.0.3.dist-info/top_level.txt
sound_to_midi-0.0.3.dist-info/RECORD
