Metadata-Version: 2.1
Name: sound-to-midi
Version: 0.0.3
Summary: Converts audio to midi.
Author-email: Tiago Tavares <tiagoft@gmail.com>
Project-URL: Homepage, https://github.com/tiagoft/audio_to_midi
Classifier: Programming Language :: Python :: 3
Classifier: License :: OSI Approved :: MIT License
Classifier: Operating System :: OS Independent
Requires-Python: >=3.7
License-File: LICENSE
